dftools/exceptions.py
dftools/api/__init__.py
dftools/api/data_compare/__init__.py
dftools/api/data_compare/compare_same_structure.py
dftools/api/data_compare/pd_df_compare.py
dftools/api/data_csv_api/__init__.py
dftools/api/data_csv_api/data_query.py
dftools/api/sql_query_api/__init__.py
dftools/api/sql_query_api/statement_gen_api.py
dftools/build/lib/utils/__init__.py
dftools/build/lib/utils/csv_loader.py
dftools/build/lib/utils/dict_decoder.py
dftools/build/lib/utils/dict_util.py
dftools/build/lib/utils/file_util.py
dftools/build/lib/utils/json_loadable.py
dftools/build/lib/utils/json_reader_util.py
dftools/build/lib/utils/json_util.py
dftools/build/lib/utils/list_util.py
dftools/build/lib/utils/string_util.py
dftools/core/check/__init__.py
dftools/core/check/check_event.py
dftools/core/check/check_rule.py
dftools/core/check/obj_check.py
dftools/core/check/regex_check_rule.py
dftools/core/check/standard_checks.py
dftools/core/compare/__init__.py
dftools/core/compare/comparator.py
dftools/core/compare/compare_events.py
dftools/core/dataflow/__init__.py
dftools/core/dataflow/definition/__init__.py
dftools/core/dataflow/definition/core/__init__.py
dftools/core/dataflow/definition/core/data_flow_def.py
dftools/core/dataflow/definition/core/data_flow_def_tmpl.py
dftools/core/dataflow/definition/core/data_flow_util.py
dftools/core/dataflow/definition/core/data_process_def.py
dftools/core/dataflow/definition/core/source_selection_def.py
dftools/core/dataflow/definition/ingestion/ingestion_data_flow_def.py
dftools/core/dataflow/definition/utils/data_def_util.py
dftools/core/dataflow/utils/__init__.py
dftools/core/dataflow/utils/attribute.py
dftools/core/dataflow/utils/characterisation.py
dftools/core/dataflow/utils/data_load_strategy_util.py
dftools/core/dataflow/utils/dataflow_namespace.py
dftools/core/dataflow/utils/parameter.py
dftools/core/dataflow/utils/variable.py
dftools/core/scheduler/core/graph.py
dftools/core/scheduler/core/task.py
dftools_core-0.1.1.dist-info/METADATA
dftools_core-0.1.1.dist-info/WHEEL
dftools_core-0.1.1.dist-info/top_level.txt
dftools_core-0.1.1.dist-info/RECORD
