Metadata-Version: 2.1
Name: dftools-core
Version: 0.1.1
Summary: Data Flooder Tools - Core Package
Author: Lirav DUVSHANI
Author-email: Lirav DUVSHANI <lirav.duvshani@dataflooder.com>
Project-URL: Homepage, https://github.com/dataflooder/dftools-core
Keywords: df,dataflooder,dftools,data,dataengineering
Classifier: License :: OSI Approved :: Apache Software License
Classifier: Programming Language :: Python :: 3.7
Classifier: Programming Language :: Python :: 3.8
Classifier: Programming Language :: Python :: 3.9
Classifier: Development Status :: 3 - Alpha
Requires-Python: >=3.7.9
Requires-Dist: strenum
Requires-Dist: regex
Requires-Dist: pandas
Requires-Dist: jinja2
Requires-Dist: ordered-set
Provides-Extra: dev
